cocat/__init__.py
cocat/api.py
cocat/app/app.py
cocat/app/db.py
cocat/app/schemas.py
cocat/app/users.py
cocat/base.py
cocat/catalogue.py
cocat/cli.py
cocat/db.py
cocat/event.py
cocat/models.py
cocat/py.typed
cocat/votable.py
cocat-0.7.0.dist-info/licenses/LICENSE
cocat-0.7.0.dist-info/WHEEL
cocat-0.7.0.dist-info/entry_points.txt
cocat-0.7.0.dist-info/METADATA
cocat-0.7.0.dist-info/RECORD
